MANIFEST.in
README.rst
setup.py
wagtailfroala/__init__.py
wagtailfroala/rich_text.py
wagtailfroala.egg-info/PKG-INFO
wagtailfroala.egg-info/SOURCES.txt
wagtailfroala.egg-info/dependency_links.txt
wagtailfroala.egg-info/requires.txt
wagtailfroala.egg-info/top_level.txt
wagtailfroala/static/froala/css/wagtailfroala.css
wagtailfroala/static/froala/js/froala.js
wagtailfroala/static/froala/vendor/css/froala_editor.css
wagtailfroala/static/froala/vendor/css/froala_editor.min.css
wagtailfroala/static/froala/vendor/css/froala_editor.pkgd.css
wagtailfroala/static/froala/vendor/css/froala_editor.pkgd.min.css
wagtailfroala/static/froala/vendor/css/froala_style.css
wagtailfroala/static/froala/vendor/css/froala_style.min.css
wagtailfroala/static/froala/vendor/css/plugins/char_counter.css
wagtailfroala/static/froala/vendor/css/plugins/char_counter.min.css
wagtailfroala/static/froala/vendor/css/plugins/code_view.css
wagtailfroala/static/froala/vendor/css/plugins/code_view.min.css
wagtailfroala/static/froala/vendor/css/plugins/colors.css
wagtailfroala/static/froala/vendor/css/plugins/colors.min.css
wagtailfroala/static/froala/vendor/css/plugins/draggable.css
wagtailfroala/static/froala/vendor/css/plugins/draggable.min.css
wagtailfroala/static/froala/vendor/css/plugins/emoticons.css
wagtailfroala/static/froala/vendor/css/plugins/emoticons.min.css
wagtailfroala/static/froala/vendor/css/plugins/file.css
wagtailfroala/static/froala/vendor/css/plugins/file.min.css
wagtailfroala/static/froala/vendor/css/plugins/fullscreen.css
wagtailfroala/static/froala/vendor/css/plugins/fullscreen.min.css
wagtailfroala/static/froala/vendor/css/plugins/image.css
wagtailfroala/static/froala/vendor/css/plugins/image.min.css
wagtailfroala/static/froala/vendor/css/plugins/image_manager.css
wagtailfroala/static/froala/vendor/css/plugins/image_manager.min.css
wagtailfroala/static/froala/vendor/css/plugins/line_breaker.css
wagtailfroala/static/froala/vendor/css/plugins/line_breaker.min.css
wagtailfroala/static/froala/vendor/css/plugins/quick_insert.css
wagtailfroala/static/froala/vendor/css/plugins/quick_insert.min.css
wagtailfroala/static/froala/vendor/css/plugins/table.css
