Metadata-Version: 1.1
Name: wagtailfroala
Version: 0.2.11
Summary: Extends Wagtail to use the Froala WYSIWYG editor in RichTextFields/RichTextBlocks.
Home-page: https://github.com/jaydensmith/wagtailfroala
Author: Jayden Smith
Author-email: jayden@intelliscale.com.au
License: MIT License
Platform: UNKNOWN
Classifier: Environment :: Web Environment
Classifier: Framework :: Django
Classifier: Framework :: Django :: 1.8
Classifier: Framework :: Django :: 1.9
Classifier: Programming Language :: Python
Classifier: Programming Language :: Python :: 3
Classifier: Programming Language :: Python :: 3.4
Classifier: Programming Language :: Python :: 3.5
Classifier: Operating System :: OS Independent
Classifier: License :: OSI Approved :: MIT License
Classifier: Intended Audience :: Developers
Classifier: Topic :: Internet :: WWW/HTTP
Classifier: Topic :: Internet :: WWW/HTTP :: Dynamic Content
